inovance_tag/__init__.py
inovance_tag/exception.py
inovance_tag/inovance_tag_dll/InoTagAccess.dll
inovance_tag/inovance_tag_dll/InoTagComCSharp.dll
inovance_tag/inovance_tag_dll/PacTagCom.dll
inovance_tag/inovance_tag_dll/RtosLib64.dll
inovance_tag/inovance_tag_dll/Tag.dll
inovance_tag/inovance_tag_dll/TagAccessCS.dll
inovance_tag/tag_communication.py
inovance_tag/tag_communication_simple.py
inovance_tag/tag_type_enum.py
inovance_tag_cyg-1.8.1.dist-info/METADATA
inovance_tag_cyg-1.8.1.dist-info/WHEEL
inovance_tag_cyg-1.8.1.dist-info/RECORD
