Metadata-Version: 2.4
Name: inovance_tag_cyg
Version: 1.8.1
Summary: inovance tag communication
Author: LiuWei
Author-email: 183074632@qq.com
Requires-Python: >=3.7,<3.13
Classifier: Programming Language :: Python :: 3
Classifier: Programming Language :: Python :: 3.7
Classifier: Programming Language :: Python :: 3.8
Classifier: Programming Language :: Python :: 3.9
Classifier: Programming Language :: Python :: 3.10
Classifier: Programming Language :: Python :: 3.11
Classifier: Programming Language :: Python :: 3.12
Requires-Dist: pythonnet (>=3.0.4,<4.0.0)
Project-URL: Homepage, https://github.com/ChangYuan-Semiconductor-Equipment/inovance_tag_cyg.git
Project-URL: Repository, https://github.com/ChangYuan-Semiconductor-Equipment/inovance_tag_cyg.git
